<?xml version="1.0" encoding="UTF-8"?><database>
    <element extends="cmdb_ci" label="Certificates" max_length="40" name="x_avx_appviewx_aut_certificates" sizeclass="0" type="collection">
        <element label="Certificate Authority" max_length="40" name="certificate_authority" read_only="true" type="string"/>
        <element label="Serial Number" max_length="40" name="cert_serialnumber" read_only="true" type="string"/>
        <element display="true" label="Common Name" max_length="40" name="common_name" read_only="true" type="string"/>
        <element label="Expiry Date" max_length="40" name="expiry_date" read_only="true" type="string"/>
        <element attributes="ignore_filter_on_new=true" default="javascript:global.getNextObjNumberPadded();" label="Number" max_length="40" name="number" read_only="true" type="string"/>
        <element label="Source" max_length="40" name="source" read_only="true" type="string"/>
        <element label="Status" max_length="40" name="status" read_only="true" type="string"/>
    </element>
</database>
